MANIFEST.in
README.md
setup.cfg
setup.py
bin/mcmc-monitor-stan
mcmc_monitor/__init__.py
mcmc_monitor/version.py
mcmc_monitor.egg-info/PKG-INFO
mcmc_monitor.egg-info/SOURCES.txt
mcmc_monitor.egg-info/dependency_links.txt
mcmc_monitor.egg-info/requires.txt
mcmc_monitor.egg-info/top_level.txt
mcmc_monitor/core/MCMCRun.py
mcmc_monitor/core/StanMonitor.py
mcmc_monitor/core/__init__.py
mcmc_monitor/core/monitor_stan_run.py
mcmc_monitor/mcmc_monitor_stan_cli/__init__.py
mcmc_monitor/mcmc_monitor_stan_cli/mcmc_monitor_stan_cli.py